docker_volume_watcher/__init__.py
docker_volume_watcher/call_debouncer.py
docker_volume_watcher/cli.py
docker_volume_watcher/container_monitor.py
docker_volume_watcher/container_notifier.py
docker_windows_volume_watcher-1.2.0.dist-info/LICENSE
docker_windows_volume_watcher-1.2.0.dist-info/METADATA
docker_windows_volume_watcher-1.2.0.dist-info/WHEEL
docker_windows_volume_watcher-1.2.0.dist-info/entry_points.txt
docker_windows_volume_watcher-1.2.0.dist-info/top_level.txt
docker_windows_volume_watcher-1.2.0.dist-info/RECORD
