Metadata-Version: 2.1
Name: docker-windows-volume-watcher
Version: 1.2.0
Summary: A tool to notify Docker contianers about changes in mounts on Windows.
Home-page: http://github.com/merofeev/docker-windows-volume-watcher
Author: Mikhail Erofeev
Author-email: mikhail@erofeev.pw
License: MIT
Keywords: Docker volume Windows watch inotify
Platform: UNKNOWN
Classifier: Intended Audience :: Developers
Classifier: Operating System :: Microsoft :: Windows
Classifier: License :: OSI Approved :: MIT License
Classifier: Programming Language :: Python :: 2.7
Classifier: Programming Language :: Python :: 3
Classifier: Topic :: Software Development
Classifier: Topic :: System :: Monitoring
Requires-Dist: watchdog (>=0.8.3)
Requires-Dist: docker (>=3.0.0)
Requires-Dist: future (>=0.17.1)
